{"oracle corporation": {"Citation Count": 6.0, "Publication Count": 0.3333333333333333}, "university of edinburgh": {"Citation Count": 27.555555555555557, "Publication Count": 1.4444444444444444}, "intel": {"Citation Count": 6.0, "Publication Count": 2.0}, "university of glasgow": {"Citation Count": 2.2222222222222223, "Publication Count": 0.1111111111111111}, "trinity college": {"Citation Count": 2.2222222222222223, "Publication Count": 0.1111111111111111}, "georgia institute of technology": {"Citation Count": 30.0, "Publication Count": 1.0}, "facebook": {"Citation Count": 0.2, "Publication Count": 0.2}, "samsung": {"Citation Count": 0.9333333333333333, "Publication Count": 0.9333333333333333}, "pennsylvania state university": {"Citation Count": 0.2, "Publication Count": 0.2}, "advanced micro devices": {"Citation Count": 3.875, "Publication Count": 1.625}, "university of waterloo": {"Citation Count": 0.125, "Publication Count": 0.125}, "ashoka university": {"Citation Count": 1.0, "Publication Count": 1.0}, "cornell university": {"Citation Count": 1.0, "Publication Count": 0.25}, "seoul national university": {"Citation Count": 3.0, "Publication Count": 1.0}, "queen s university belfast": {"Citation Count": 4.0, "Publication Count": 0.8}, "virginia tech": {"Citation Count": 1.0, "Publication Count": 0.2}, "national and kapodistrian university of athens": {"Citation Count": 4.0, "Publication Count": 1.0}, "university of toronto": {"Citation Count": 2.0, "Publication Count": 1.0}, "drexel university": {"Citation Count": 1.2000000000000002, "Publication Count": 0.4}, "tufts university": {"Citation Count": 1.7999999999999998, "Publication Count": 0.6}, "university of rochester": {"Citation Count": 1.0, "Publication Count": 0.3333333333333333}, "university of california santa cruz": {"Citation Count": 1.0, "Publication Count": 0.3333333333333333}, "imperial college london": {"Citation Count": 1.0, "Publication Count": 0.3333333333333333}, "google": {"Citation Count": 0.875, "Publication Count": 0.125}, "massachusetts institute of technology": {"Citation Count": 6.125, "Publication Count": 0.875}, "ohio state university": {"Citation Count": 4.0, "Publication Count": 1.0}, "alibaba group": {"Citation Count": 12.0, "Publication Count": 0.8571428571428571}, "university of hong kong": {"Citation Count": 2.0, "Publication Count": 0.14285714285714285}, "university of virginia": {"Citation Count": 2.0, "Publication Count": 1.0}, "kaist": {"Citation Count": 0.0, "Publication Count": 1.0}, "george washington university": {"Citation Count": 0.14285714285714285, "Publication Count": 0.14285714285714285}, "university of central florida": {"Citation Count": 0.7142857142857143, "Publication Count": 0.7142857142857143}, "university of california riverside": {"Citation Count": 0.14285714285714285, "Publication Count": 0.14285714285714285}, "university of california san diego": {"Citation Count": 0.6666666666666666, "Publication Count": 0.6666666666666666}, "clemson university": {"Citation Count": 0.5, "Publication Count": 0.5}, "pacific northwest national laboratory": {"Citation Count": 0.5, "Publication Count": 0.5}, "ibm": {"Citation Count": 1.0, "Publication Count": 1.0}, "boston university": {"Citation Count": 0.3333333333333333, "Publication Count": 0.16666666666666666}, "university of minnesota": {"Citation Count": 1.0, "Publication Count": 0.5}, "brown university": {"Citation Count": 0.6666666666666666, "Publication Count": 0.3333333333333333}, "north carolina state university": {"Citation Count": 0.0, "Publication Count": 1.0}}