{"online multi task gradient temporal difference learning": {"filter": "Header Section", "author": ["Vishnu Purushothaman Sreenivasan", "Haitham Bou-Ammar", "Eric Eaton"]}, "communication restricted exploration for small teams": {"filter": "Header Section", "author": ["Elizabeth A. Jensen", "Ken Sugawara"]}, "the effect of similarity between human and machine action choices on adaptive automation performance": {"filter": "Header Section", "author": ["Jason M. Bindewald"]}, "fast algorithm for non stationary gaussian process prediction": {"filter": "Header Section", "author": ["Yulai Zhang", "Guiming Luo"]}, "inferring causal directions in errors in variables models": {"filter": "Header Section", "author": ["Yulai Zhang", "Guiming Luo"]}, "jim a platform for affective ai in an interdisciplinary setting": {"filter": "Header Section", "author": ["Robert Selkowitz", "Michael Heilemann", "Jon Mrowczynski"]}, "genotypic versus behavioural diversity for teams of programs under the 4 v 3 keepaway soccer task": {"filter": "Header Section", "author": ["Stephen Kelly", "Malcolm I. Heywood"]}, "association rule hiding based on evolutionary multi objective optimization by removing items": {"filter": "Header Section", "author": ["Peng Cheng", "Jeng-Shyang Pan"]}, "a knowledge representation that models memory in narrative comprehension": {"filter": "Header Section", "author": ["Rogelio Enrique Cardona-Rivera", "Robert Michael Young"]}, "optimizing and learning diffusion behaviors in complex network": {"filter": "Header Section", "author": ["Xiaojian Wu"]}, "coordination of multiple teams of robots for an optimal global plan": {"filter": "Header Section", "author": ["Zeynep Gozen Saribatur", "Esra Erdem", "Volkan Patoglu"]}, "lsdh a hashing approach for large scale link prediction in microblogs": {"filter": "Header Section", "author": ["Dawei Liu", "Yuanzhuo Wang", "Yantao Jia", "Jingyuan Li", "Zhihua Yu"]}, "reprev mitigating the negative effects of misreported ratings": {"filter": "Header Section", "author": ["Yuan Liu", "Siyuan Liu", "Jie Zhang", "Hui Fang", "Han Yu", "Chunyan Miao"]}, "crowdsourced explanations for humorous internet memes": {"filter": "Header Section", "author": ["Chi-Chin Lin", "Jane Yung-jen Hsu"]}, "identifying domain dependent influential microblog users a post feature based approach": {"filter": "Header Section", "author": ["Nian Liu", "Lin Li", "Guandong Xu", "Zhenglu Yang"]}, "advice provision for choice selection processes with ranked options": {"filter": "Header Section", "author": ["Amos Azaria", "Ya'akov Gal", "Claudia V. Goldman", "Sarit Kraus"]}, "converting instance checking to subsumption a rethink for object queries over practical ontologies": {"filter": "Header Section", "author": ["Jia Xu", "Ubbo Visser", "Mansur R. Kabuka"]}, "reinforcement learning on multiple correlated signals": {"filter": "Header Section", "author": ["Tim Brys", "Ann Nowe"]}, "a novel single dbn generative model for optimizing pomdp controllers by probabilistic inference": {"filter": "Header Section", "author": ["Igor Kiselev", "Pascal Poupart"]}, "roles and teams hedonic games": {"filter": "Header Section", "author": ["Matthew Spradling"]}, "robot team exploration with communication restrictions": {"filter": "Header Section", "author": ["Elizabeth A. Jensen"]}, "computing preferences based on agents  beliefs": {"filter": "Header Section", "author": ["Jian Luo", "Fuan Pu", "Yulai Zhang", "Guiming Luo"]}, "living and searching in the world object based state estimation for mobile robots": {"filter": "Header Section", "author": ["Lawson L. S. Wong"]}, "a model for aggregating contributions of synergistic crowdsourcing workflows": {"filter": "Header Section", "author": ["Yili Fang", "Hailong Sun", "Richong Zhang", "Jinpeng Huai", "Yongyi Mao"]}, "content structural relation inference in knowledge base": {"filter": "Header Section", "author": ["Zeya Zhao", "Yantao Jia", "Yuanzhuo Wang"]}, "solving semantic problems using contexts extracted from knowledge graphs": {"filter": "Header Section", "author": ["Adrian Boteanu"]}, "the semantic interpretation of trust in multiagent interactions": {"filter": "Header Section", "author": ["Anup K. Kalia"]}, "imputation social choice and partial preferences": {"filter": "Header Section", "author": ["John A. Doucette"]}, "to share or not to share the single agent in a team decision problem": {"filter": "Header Section", "author": ["Ofra Amir", "Barbara J. Grosz", "Roni Stern"]}, "monte carlo simulation adjusting": {"filter": "Header Section", "author": ["Nobuo Araki", "Masakazu Muramatsu", "Kunihito Hoki", "Satoshi Takahashi"]}, "partial satisfaction planning under time uncertainty with control on when objectives can be aborted": {"filter": "Header Section", "author": ["Sylvain Labranche", "Eric Beaudry"]}, "data clustering by laplacian regularized l1 graph": {"filter": "Header Section", "author": ["Yingzhen Yang", "Zhangyang Wang", "Jianchao Yang", "Jiangping Wang", "Shiyu Chang", "Thomas S. Huang"]}, "a data complexity approach to kernel selection for support vector machines": {"filter": "Header Section", "author": ["Roberto Valerio", "Ricardo Vilalta"]}, "compilation based approaches to probabilistic planning thesis summary": {"filter": "Header Section", "author": ["Ran Taig"]}, "a model attention and selection framework for estimation of many variables with applications to estimating object states in large spatial environments": {"filter": "Header Section", "author": ["Lawson L. S. Wong"]}, "representing words as lymphocytes": {"filter": "Header Section", "author": ["Jinfeng Yang", "Yi Guan", "Xishuang Dong", "Bin He"]}, "uncovering hidden structure through parallel problem decomposition": {"filter": "Header Section", "author": ["Yexiang Xue", "Stefano Ermon", "Carla P. Gomes", "Bart Selman"]}, "event recommendation in event based social networks": {"filter": "Header Section", "author": ["Zhi Qiao", "Peng Zhang", "Chuan Zhou", "Yanan Cao", "Li Guo", "Yanchuan Zhang"]}, "online search algorithm configuration": {"filter": "Header Section", "author": ["Tadhg Fitzgerald", "Barry O'Sullivan", "Yuri Malitsky", "Kevin Tierney"]}, "making cp nets more useful": {"filter": "Header Section", "author": ["Thomas E. Allen"]}, "analogy tutor a tutoring system for promoting conceptual learning via comparison": {"filter": "Header Section", "author": ["Maria de los Angeles Chang"]}, "probabilistic planning with reduced models": {"filter": "Header Section", "author": ["Luis Enrique Pineda"]}, "modeling argumentation and explanation in the social web": {"filter": "Header Section", "author": ["Taraneh Khazaei"]}, "addressing complexity in multi issue negotiation via utility hypergraphs": {"filter": "Header Section", "author": ["Rafik Hadfi", "Takayuki Ito"]}, "easychair as a pedagogical tool engaging graduate students in the reviewing process": {"filter": "Header Section", "author": ["Kartik Talamadupula", "Subbarao Kambhampati"]}, "information sharing for care coordination": {"filter": "Header Section", "author": ["Ofra Amir"]}, "social capital in network organizations": {"filter": "Header Section", "author": ["Saad Alqithami", "Henry Hexmoor"]}, "inference graphs a new kind of hybrid reasoning system": {"filter": "Header Section", "author": ["Daniel R. Schlegel", "Stuart C. Shapiro"]}, "semantical clustering of morphologically related chinese words": {"filter": "Header Section", "author": ["Chia-Ling Lee", "Ya-Ning Chang", "Chao-Lin Liu", "Chia-Ying Lee", "Jane Yung-jen Hsu"]}, "reputation aware continuous double auction": {"filter": "Header Section", "author": ["Yuan Liu", "Jie Zhang", "Han Yu", "Chunyan Miao"]}, "automatically creating multilingual lexical resources": {"filter": "Header Section", "author": ["Khang Nhut Lam"]}}